{"3L-code":"HRV","country_name":"Croatia","active_country_area_km2":54740,"Edge_No":21749,"Node_No":14924,"Density":0.0001953115,"Clique_No":4.0,"Ave_Path_Length":68.6887279062,"Assortativity":0.0706503753,"Diameter":180.0,"Edge_Connectivity":0.0,"Max_Degree":8,"Total_Edge_Length":31087684.7655754127,"Len_Motorway":2841,"Len_Primary":7305,"Len_Secondary":10974,"Len_Tertiary":9469,"Len_Trunk":497,"Len_tot__km":31087,"Len_PRIM":10643,"Edge_count":21749,"Edgecount_PRIM":3042,"i_hit_PRIM_COUNT":1750,"i_hit_PRIM_LEN":3493,"i_hit_ALL_COUNT":4155,"i_hit_ALL_LEN":8542,"i_0cm_PRIM_COUNT":1601,"i_0cm_PRIM_LEN":2844,"i_0cm_ALL_COUNT":3696,"i_0cm_ALL_LEN":6720,"i_50cm_PRIM_COUNT":1469,"i_50cm_PRIM_LEN":2765,"i_50cm_ALL_COUNT":3374,"i_50cm_ALL_LEN":6492,"i_100cm_PRIM_COUNT":1336,"i_100cm_PRIM_LEN":2694,"i_100cm_ALL_COUNT":3042,"i_100cm_ALL_LEN":6267,"FPL_mode":100.0,"FPL_mean":77.3044524669,"FPL_median":100.0}